miniball.py
miniball-1.0.3.dist-info/LICENSE
miniball-1.0.3.dist-info/METADATA
miniball-1.0.3.dist-info/WHEEL
miniball-1.0.3.dist-info/top_level.txt
miniball-1.0.3.dist-info/RECORD
