Metadata-Version: 2.1
Name: miniball
Version: 1.0.3
Summary: Efficiently computes the smallest bounding ball of a point set, in arbitrary number of dimensions.
Home-page: https://github.com/marmakoide/miniball
Author: Alexandre Devert
Author-email: marmakoide@hotmail.fr
License: MIT
Platform: UNKNOWN
Classifier: Development Status :: 5 - Production/Stable
Classifier: Programming Language :: Python :: 2
Classifier: Programming Language :: Python :: 3
Classifier: Intended Audience :: Developers
Classifier: Intended Audience :: Science/Research
Classifier: License :: OSI Approved :: MIT License
Classifier: Topic :: Scientific/Engineering :: Mathematics
Classifier: Topic :: Software Development :: Libraries
Classifier: Topic :: Utilities
Requires-Python: >=2.7, !=3.0.*, !=3.1.*
Requires-Dist: numpy
